Metrohm/AUTOLAB.py
Metrohm/__init__.py
pyMetrohmAUTOLAB-0.0.4.dist-info/LICENSE
pyMetrohmAUTOLAB-0.0.4.dist-info/METADATA
pyMetrohmAUTOLAB-0.0.4.dist-info/WHEEL
pyMetrohmAUTOLAB-0.0.4.dist-info/top_level.txt
pyMetrohmAUTOLAB-0.0.4.dist-info/RECORD
