Metadata-Version: 2.1
Name: pyMetrohmAUTOLAB
Version: 0.0.4
Summary: A tool to using Metrohm AUTOLAB SDK in Python(it is still under heavily developed)
Home-page: https://github.com/shuayliu/pyMetrohmAUTOLAB
Author: Jonah Liu
Author-email: jonahliu@outlook.com
License: UNKNOWN
Project-URL: Bug Tracker, https://github.com/shuayliu/pyMetrohmAUTOLAB/issues
Platform: UNKNOWN
Classifier: Programming Language :: Python :: 3
Classifier: License :: OSI Approved :: MIT License
Classifier: Operating System :: Microsoft :: Windows
Classifier: Topic :: Scientific/Engineering
Classifier: Intended Audience :: Science/Research
Requires-Python: >=3.6
License-File: LICENSE
Requires-Dist: pythonnet
Requires-Dist: numpy
